escriptorium_connector/__init__.py
escriptorium_connector/connector.py
escriptorium_connector/connector_errors.py
escriptorium_connector/convenience_functions/__init__.py
escriptorium_connector/convenience_functions/copy_document.py
escriptorium_connector/dtos/__init__.py
escriptorium_connector/dtos/annotation_dtos.py
escriptorium_connector/dtos/document_dtos.py
escriptorium_connector/dtos/escriptorium_schema.py
escriptorium_connector/dtos/line_dtos.py
escriptorium_connector/dtos/part_dtos.py
escriptorium_connector/dtos/project_dtos.py
escriptorium_connector/dtos/region_dtos.py
escriptorium_connector/dtos/super_dtos.py
escriptorium_connector/dtos/transcription_dtos.py
escriptorium_connector/dtos/user_dtos.py
escriptorium_connector/utils/__init__.py
escriptorium_connector/utils/html_analysis.py
escriptorium_connector/utils/pydantic_dataclass_fix.py
escriptorium_connector/utils/timeout_websocket_client.py
escriptorium_connector-0.2.6.dist-info/LICENSE
escriptorium_connector-0.2.6.dist-info/WHEEL
escriptorium_connector-0.2.6.dist-info/METADATA
escriptorium_connector-0.2.6.dist-info/RECORD
