Metadata-Version: 2.1
Name: escriptorium-connector
Version: 0.2.6
Summary: This simple python package makes it easy to connect to an eScriptorium instance and to work with the data there.
Home-page: https://gitlab.com/sofer_mahir/escriptorium_python_connector
License: MIT
Keywords: escriptorium,api
Author: Bronson Brown-deVost
Author-email: bronsonbdevost@gmail.com
Requires-Python: >=3.7,<4.0
Classifier: License :: OSI Approved :: MIT License
Classifier: Programming Language :: Python :: 3
Classifier: Programming Language :: Python :: 3.10
Classifier: Programming Language :: Python :: 3.7
Classifier: Programming Language :: Python :: 3.8
Classifier: Programming Language :: Python :: 3.9
Requires-Dist: alive-progress (>=2.1.0,<3.0.0)
Requires-Dist: bs4 (>=0.0.1,<0.0.2)
Requires-Dist: colorama (>=0.4.4,<0.5.0)
Requires-Dist: lxml (>=4.6.4,<5.0.0)
Requires-Dist: pydantic (>=1.8.2,<2.0.0)
Requires-Dist: requests (==2.28.2)
Requires-Dist: websocket-client (>=1.2.1,<2.0.0)
Project-URL: Repository, https://gitlab.com/sofer_mahir/escriptorium_python_connector
